nsdf_dark_matter/__init__.py
nsdf_dark_matter/idx.py
nsdf_dark_matter/py.typed
nsdf_dark_matter-0.3.0.dist-info/METADATA
nsdf_dark_matter-0.3.0.dist-info/WHEEL
nsdf_dark_matter-0.3.0.dist-info/RECORD
