Metadata-Version: 2.4
Name: nsdf-dark-matter
Version: 0.3.0
Summary: Library for reading and processing dark matter data in IDX format
Project-URL: documentation, https://nsdf-fabric.github.io/nsdf-slac/
Project-URL: source, https://github.com/nsdf-fabric/nsdf-slac
Project-URL: tracker, https://github.com/nsdf-fabric/nsdf-slac/issues
Project-URL: release notes, https://github.com/nsdf-fabric/nsdf-slac/releases
Author-email: NSDF Team <info@nationalsciencedatafabric.org>
Classifier: Intended Audience :: Developers
Classifier: Intended Audience :: Science/Research
Classifier: Programming Language :: Python
Classifier: Programming Language :: Python :: 3.10
Classifier: Topic :: Scientific/Engineering
Classifier: Topic :: Software Development
Requires-Python: >=3.10
Requires-Dist: numpy
Requires-Dist: openvisusnogui==2.2.138
